plugin_module.py
count_label_changes-0.1.3.dist-info/LICENSE
count_label_changes-0.1.3.dist-info/METADATA
count_label_changes-0.1.3.dist-info/WHEEL
count_label_changes-0.1.3.dist-info/entry_points.txt
count_label_changes-0.1.3.dist-info/top_level.txt
count_label_changes-0.1.3.dist-info/RECORD
