Metadata-Version: 2.2
Name: count-label-changes
Version: 0.1.3
Summary: A plugin for Nellie that counts label changes. One type of typically used fission and fusion metric.
Home-page: https://github.com/aelefebv/nellie-plugin-fission-fusion
Author: Austin E. Y. T. Lefebvre
Author-email: austin.e.lefebvre+nellie@gmail.com
Classifier: Programming Language :: Python :: 3
Classifier: License :: OSI Approved :: MIT License
Classifier: Operating System :: OS Independent
Requires-Python: >=3.9
License-File: LICENSE
Requires-Dist: nellie
Requires-Dist: pandas
Dynamic: author
Dynamic: author-email
Dynamic: classifier
Dynamic: description
Dynamic: description-content-type
Dynamic: home-page
Dynamic: requires-dist
Dynamic: requires-python
Dynamic: summary
